menderbot/__init__.py
menderbot/__main__.py
menderbot/check.py
menderbot/code.py
menderbot/config.py
menderbot/doc.py
menderbot/git_client.py
menderbot/ingest.py
menderbot/llm.py
menderbot/prompts.py
menderbot/source_file.py
menderbot/typing.py
menderbot/antlr_generated/PythonLexer.py
menderbot/antlr_generated/PythonLexerBase.py
menderbot/antlr_generated/PythonParser.py
menderbot/antlr_generated/PythonParserBase.py
menderbot/antlr_generated/PythonParserListener.py
menderbot/antlr_generated/__init__.py
menderbot-0.0.4.dist-info/LICENSE
menderbot-0.0.4.dist-info/METADATA
menderbot-0.0.4.dist-info/WHEEL
menderbot-0.0.4.dist-info/entry_points.txt
menderbot-0.0.4.dist-info/top_level.txt
menderbot-0.0.4.dist-info/RECORD
