Metadata-Version: 2.1
Name: menderbot
Version: 0.0.4
Summary: The AI-powered command line tool for working with legacy code
Author: Ray Myers
License: Apache License
Project-URL: Homepage, https://github.com/craftvscruft/menderbot
Keywords: ai,gpt,refactoring,legacy,code
Platform: Linux
Platform: Mac OSX
Platform: Windows
Classifier: License :: OSI Approved :: Apache Software License
Classifier: Programming Language :: Python
Classifier: Programming Language :: Python :: 3
Classifier: Development Status :: 3 - Alpha
Classifier: Topic :: Scientific/Engineering :: Artificial Intelligence
Classifier: Topic :: Software Development :: Quality Assurance
Classifier: Topic :: Software Development :: Documentation
Classifier: Topic :: Software Development :: Code Generators
Requires-Python: >=3.9
License-File: LICENSE
Requires-Dist: click >=8.0.0
Requires-Dist: rich-click >=1.6.0
Requires-Dist: charset-normalizer >=3.2.0
Requires-Dist: tiktoken
Requires-Dist: llama-index >=0.7.12
Requires-Dist: rich-click
Requires-Dist: gitpython
Requires-Dist: antlr4-python3-runtime
Requires-Dist: nltk >=3.0.0
Provides-Extra: dev
Requires-Dist: black ; extra == 'dev'
Requires-Dist: bump2version ; extra == 'dev'
Requires-Dist: isort ; extra == 'dev'
Requires-Dist: pip-tools ; extra == 'dev'
Requires-Dist: pytest ; extra == 'dev'
Requires-Dist: approvaltests ; extra == 'dev'
Requires-Dist: pytest-approvaltests ; extra == 'dev'
Requires-Dist: pylint ; extra == 'dev'
Requires-Dist: mypy ; extra == 'dev'
Requires-Dist: markdown-code-runner ; extra == 'dev'
Requires-Dist: pytest-cov ; extra == 'dev'
Requires-Dist: types-PyYAML ; extra == 'dev'
